python_touch/__init__.py
python_touch/cli.py
python_touch-0.1.1.dist-info/entry_points.txt
python_touch-0.1.1.dist-info/LICENSE
python_touch-0.1.1.dist-info/WHEEL
python_touch-0.1.1.dist-info/METADATA
python_touch-0.1.1.dist-info/RECORD
