Metadata-Version: 2.1
Name: python-touch
Version: 0.1.1
Summary: 
License: MIT
Author: takeshi0406
Author-email: sci.and.eng@gmail.com
Requires-Python: >=3.7,<4.0
Classifier: License :: OSI Approved :: MIT License
Classifier: Programming Language :: Python :: 3
Classifier: Programming Language :: Python :: 3.7
Classifier: Programming Language :: Python :: 3.8
Requires-Dist: click (>=7.1.2,<8.0.0)
